flaskOne/__init__.py
flaskOne-0.3.dist-info/METADATA
flaskOne-0.3.dist-info/WHEEL
flaskOne-0.3.dist-info/entry_points.txt
flaskOne-0.3.dist-info/top_level.txt
flaskOne-0.3.dist-info/RECORD
